example_pkg/__init__.py
gotrans/__init__.py
gotrans/translate.py
quotool/__init__.py
quotool/quo_down.py
quotool-0.0.5.dist-info/LICENSE
quotool-0.0.5.dist-info/LICENSE.example
quotool-0.0.5.dist-info/METADATA
quotool-0.0.5.dist-info/WHEEL
quotool-0.0.5.dist-info/top_level.txt
quotool-0.0.5.dist-info/RECORD
